{
    "name": "UserSession",
    "line": 4,
    "short_desc": "",
    "long_desc": "",
    "hint": null,
    "tags": [],
    "namespace": "",
    "file": "\/home\/wap38\/sites\/restaurant\/www\/config\/..\/application\/classes\/UserSession.class.php",
    "relative_file": null,
    "hash": "4e1489141bf7cc68fba75b3d59eac8bcd305788f",
    "parent": null,
    "modifiers": 0,
    "is_trait": false,
    "is_interface": false,
    "aliases": null,
    "errors": [],
    "interfaces": [],
    "traits": [],
    "properties": [],
    "methods": {
        "__construct": {
            "name": "__construct",
            "line": 6,
            "short_desc": "",
            "long_desc": "",
            "hint": null,
            "hint_desc": null,
            "tags": [],
            "modifiers": 1,
            "is_by_ref": "",
            "exceptions": [],
            "errors": [],
            "parameters": []
        },
        "create": {
            "name": "create",
            "line": 20,
            "short_desc": "Cr\u00e9er le tableau de Session ($_SESSION) au moment de la connexion de l'utilisateur.",
            "long_desc": "",
            "hint": [
                [
                    "\\[void]",
                    false
                ]
            ],
            "hint_desc": "[Pas de return]",
            "tags": [],
            "modifiers": 1,
            "is_by_ref": "",
            "exceptions": [],
            "errors": [],
            "parameters": {
                "sessionArray": {
                    "name": "sessionArray",
                    "line": 20,
                    "short_desc": "[contenu de la requ\u00eate SQL permettant la connexion]",
                    "long_desc": null,
                    "hint": [
                        [
                            "\\[array]",
                            false
                        ]
                    ],
                    "tags": [],
                    "modifiers": null,
                    "default": null,
                    "is_by_ref": false
                }
            }
        },
        "destroy": {
            "name": "destroy",
            "line": 37,
            "short_desc": "",
            "long_desc": "",
            "hint": null,
            "hint_desc": null,
            "tags": [],
            "modifiers": 1,
            "is_by_ref": "",
            "exceptions": [],
            "errors": [],
            "parameters": []
        },
        "getEmail": {
            "name": "getEmail",
            "line": 54,
            "short_desc": "",
            "long_desc": "",
            "hint": null,
            "hint_desc": null,
            "tags": [],
            "modifiers": 1,
            "is_by_ref": "",
            "exceptions": [],
            "errors": [],
            "parameters": []
        },
        "getFirstName": {
            "name": "getFirstName",
            "line": 64,
            "short_desc": "",
            "long_desc": "",
            "hint": null,
            "hint_desc": null,
            "tags": [],
            "modifiers": 1,
            "is_by_ref": "",
            "exceptions": [],
            "errors": [],
            "parameters": []
        },
        "getFullName": {
            "name": "getFullName",
            "line": 74,
            "short_desc": "",
            "long_desc": "",
            "hint": null,
            "hint_desc": null,
            "tags": [],
            "modifiers": 1,
            "is_by_ref": "",
            "exceptions": [],
            "errors": [],
            "parameters": []
        },
        "getLastName": {
            "name": "getLastName",
            "line": 84,
            "short_desc": "",
            "long_desc": "",
            "hint": null,
            "hint_desc": null,
            "tags": [],
            "modifiers": 1,
            "is_by_ref": "",
            "exceptions": [],
            "errors": [],
            "parameters": []
        },
        "getUserId": {
            "name": "getUserId",
            "line": 94,
            "short_desc": "",
            "long_desc": "",
            "hint": null,
            "hint_desc": null,
            "tags": [],
            "modifiers": 1,
            "is_by_ref": "",
            "exceptions": [],
            "errors": [],
            "parameters": []
        },
        "isAuthenticated": {
            "name": "isAuthenticated",
            "line": 104,
            "short_desc": "",
            "long_desc": "",
            "hint": null,
            "hint_desc": null,
            "tags": [],
            "modifiers": 1,
            "is_by_ref": "",
            "exceptions": [],
            "errors": [],
            "parameters": []
        },
        "getAll": {
            "name": "getAll",
            "line": 124,
            "short_desc": "Renvoi le contenu du tableau de Session dans une variable Render. Cette variable doit \u00eatre retourn\u00e9e dans la m\u00e9thode HttpGetMethod du Controller pour permettre le maintien de la connexion. La commande a ex\u00e9cuter dans le controller est la suivante :\n$render = (new UserSession)->getAll();\nCette commande doit \u00eatre pr\u00e9sente au d\u00e9part de chacune des class de type controller.",
            "long_desc": "",
            "hint": [
                [
                    "\\[array]",
                    false
                ]
            ],
            "hint_desc": "[$render est un tableau associatif auquel a \u00e9t\u00e9 ajout\u00e9 une clef 'user' si l'utilisateur est connect\u00e9. Dans le cas contraire, celui-ci est vide.]",
            "tags": [],
            "modifiers": 1,
            "is_by_ref": "",
            "exceptions": [],
            "errors": [],
            "parameters": {
                "render": {
                    "name": "render",
                    "line": 124,
                    "short_desc": "[contenu du $render]",
                    "long_desc": null,
                    "hint": [
                        [
                            "array",
                            false
                        ]
                    ],
                    "tags": [],
                    "modifiers": "array",
                    "default": "[]",
                    "is_by_ref": false
                }
            }
        }
    },
    "constants": []
}